  {
    "dishes": [{
        "id": "d1",
        "name": "Pad Thai Classic",
        "ingredients":
          "stir-fry dish made with rice noodles, shrimp, chicken, or tofu, peanuts,a scrambled egg and bean sprouts",
        "price": 50,
        "discount": 100
      }, {
        "id": "d2",
        "name": "Pad Thai Spicy",
        "ingredients":
          "stir-fry dish made with rice noodles, shrimp, chicken, or tofu, peanuts,a scrambled egg and bean sprouts",
        "price": 80,
        "discount": 80
      },
      {
        "id": "d2",
        "name": "Thai Chicken Satay",
        "ingredients":
          "Satay is popular throughout Southeast Asia, and this Thai satay recipe offers a traditional taste",
        "price": 150,
        "discount": 0
      },
      {
        "id": "d2",
        "name": "Pad Thai Spicy",
        "ingredients":
          "stir-fry dish made with rice noodles, shrimp, chicken, or tofu, peanuts,a scrambled egg and bean sprouts",
        "price": 50,
        "discount": 100
      },
      {
        "id": "d2",
        "name": "Pad Thai Spicy",
        "ingredients":
          "stir-fry dish made with rice noodles, shrimp, chicken, or tofu, peanuts,a scrambled egg and bean sprouts",
        "price": 50,
        "discount": 100
      },
      {
        "id": "d2",
        "name": "Pad Thai Spicy",
        "ingredients":
          "stir-fry dish made with rice noodles, shrimp, chicken, or tofu, peanuts,a scrambled egg and bean sprouts",
        "price": 50,
        "discount": 100
      },
      {
        "id": "d2",
        "name": "Pad Thai Spicy",
        "ingredients":
          "stir-fry dish made with rice noodles, shrimp, chicken, or tofu, peanuts,a scrambled egg and bean sprouts",
        "price": 50,
        "discount": 100
      },
      {
        "id": "d2",
        "name": "Pad Thai Spicy",
        "ingredients":
          "stir-fry dish made with rice noodles, shrimp, chicken, or tofu, peanuts,a scrambled egg and bean sprouts",
        "price": 50,
        "discount": 100
      },
      {
        "id": "d2",
        "name": "Pad Thai Spicy",
        "ingredients":
          "stir-fry dish made with rice noodles, shrimp, chicken, or tofu, peanuts,a scrambled egg and bean sprouts",
        "price": 50,
        "discount": 100
      }

    ]
  }
